basketball_charts/__init__.py
basketball_charts/main.py
basketball_charts-0.0.3.dist-info/LICENSE
basketball_charts-0.0.3.dist-info/METADATA
basketball_charts-0.0.3.dist-info/WHEEL
basketball_charts-0.0.3.dist-info/top_level.txt
basketball_charts-0.0.3.dist-info/RECORD
